dagger_contrib/__init__.py
dagger_contrib/serializer/__init__.py
dagger_contrib/serializer/as_yaml.py
dagger_contrib/serializer/dask/__init__.py
dagger_contrib/serializer/dask/dataframe/__init__.py
dagger_contrib/serializer/dask/dataframe/as_csv.py
dagger_contrib/serializer/dask/dataframe/as_parquet.py
dagger_contrib/serializer/pandas/__init__.py
dagger_contrib/serializer/pandas/dataframe/__init__.py
dagger_contrib/serializer/pandas/dataframe/as_csv.py
dagger_contrib/serializer/pandas/dataframe/as_parquet.py
dagger_contrib/serializer/path/__init__.py
dagger_contrib/serializer/path/as_tar.py
dagger_contrib/serializer/path/as_zip.py
py_dagger_contrib-0.4.0.dist-info/LICENSE
py_dagger_contrib-0.4.0.dist-info/WHEEL
py_dagger_contrib-0.4.0.dist-info/METADATA
py_dagger_contrib-0.4.0.dist-info/RECORD
