Metadata-Version: 2.1
Name: py-dagger-contrib
Version: 0.4.0
Summary: Extensions for the Dagger library (py-dagger in PyPI).
Home-page: https://github.com/larribas/dagger-contrib
License: Apache-2.0
Keywords: dagger,py-dagger,data-engineering,data-pipelines,data-science
Author: larribas
Author-email: lorenzo.s.arribas@gmail.com
Requires-Python: >=3.8,<3.11
Classifier: Development Status :: 4 - Beta
Classifier: Intended Audience :: Developers
Classifier: License :: OSI Approved :: Apache Software License
Classifier: Natural Language :: English
Classifier: Programming Language :: Python :: 3
Classifier: Programming Language :: Python :: 3 :: Only
Classifier: Programming Language :: Python :: 3.10
Classifier: Programming Language :: Python :: 3.8
Classifier: Programming Language :: Python :: 3.9
Classifier: Topic :: Software Development :: Build Tools
Provides-Extra: all
Provides-Extra: dask
Provides-Extra: pandas
Provides-Extra: yaml
Requires-Dist: PyYAML (>=5.4,<6.0); extra == "yaml" or extra == "all"
Requires-Dist: dask[dataframe] (>=2021.9,<2022.0); extra == "dask" or extra == "all"
Requires-Dist: pandas (>=1.3,<2.0); extra == "pandas" or extra == "dask" or extra == "all"
Requires-Dist: py-dagger (>=0.4,<0.5)
Project-URL: Repository, https://github.com/larribas/dagger-contrib
